mt/keras/__init__.py
mt/keras_src/__init__.py
mt/keras_src/base.py
mt/keras_src/applications_src/__init__.py
mt/keras_src/applications_src/classifier.py
mt/keras_src/applications_src/mobilenet_v3_split.py
mt/keras_src/applications_src/mobilevit.py
mt/keras_src/constraints_src/__init__.py
mt/keras_src/constraints_src/center_around.py
mt/keras_src/layers_src/__init__.py
mt/keras_src/layers_src/counter.py
mt/keras_src/layers_src/floor.py
mt/keras_src/layers_src/identical.py
mt/keras_src/layers_src/image_sizing.py
mt/keras_src/layers_src/normed_conv2d.py
mt/keras_src/layers_src/simple_mha.py
mt/keras_src/layers_src/soft_bend.py
mt/keras_src/layers_src/transformer_encoder.py
mt/keras_src/layers_src/utils.py
mt/keras_src/layers_src/var_regularizer.py
mt/tf/__init__.py
mt/tf/init.py
mt/tf/mttf_version.py
mt/tf/utils.py
mt/tf/version.py
mt/tf/keras_applications/__init__.py
mt/tf/keras_layers/__init__.py
mt/tfc/__init__.py
mt/tfg/__init__.py
mt/tfp/__init__.py
mt/tfp/real_nvp.py
mttf-1.2.29.data/scripts/dmt_pipi.sh
mttf-1.2.29.data/scripts/dmt_twineu.sh
mttf-1.2.29.data/scripts/pipi.sh
mttf-1.2.29.data/scripts/wml_nexus.py
mttf-1.2.29.data/scripts/wml_pipi.sh
mttf-1.2.29.data/scripts/wml_twineu.sh
mttf-1.2.29.dist-info/licenses/LICENSE
mttf-1.2.29.dist-info/METADATA
mttf-1.2.29.dist-info/WHEEL
mttf-1.2.29.dist-info/top_level.txt
mttf-1.2.29.dist-info/RECORD
