Metadata-Version: 2.4
Name: mttf
Version: 1.2.29
Summary: A package to detect and monkey-patch TensorFlow and Keras, for Minh-Tri Pham
Home-page: https://github.com/inteplus/mttf
Author: ['Minh-Tri Pham']
Project-URL: Documentation, https://mtdoc.readthedocs.io/en/latest/mt.tf/mt.tf.html
Project-URL: Source Code, https://github.com/inteplus/mttf
License-File: LICENSE
Requires-Dist: pyyaml
Requires-Dist: mtbase>=4.33.0
Requires-Dist: mtnet>=0.3.2
Dynamic: author
Dynamic: home-page
Dynamic: license-file
Dynamic: project-url
Dynamic: requires-dist
Dynamic: summary
